{
  "plugin_name": "ACL",
  "project_name": "NetBox {{ cookiecutter.plugin_name }} Plugin",
  "project_slug": "{{ cookiecutter.project_name.lower().replace(' ', '_').replace('-', '_') }}",
  "project_short_description": "NetBox plugin for {{ cookiecutter.plugin_name }}.",
  "_model_name": "{{ cookiecutter.plugin_name.replace(' ', '').replace('-', '') }}",
  "_model_url": "{{ cookiecutter.plugin_name.lower().replace(' ', '-').replace('_', '-') }}",
  "_model_url_name": "{{ cookiecutter.plugin_name.lower().replace(' ', '').replace('_', '').replace('-', '') }}",
  "full_name": "Arthur Hanson",
  "email": "ahanson@netboxlabs.com",
  "github_username": "arthanson",
  "version": "0.1.0",
  "open_source_license": ["Apache-2.0", "MIT", "BSD", "ISC", "GPL-3.0-only", "Not open source"],
  "install_precommit_hooks": "y"
}
